{"cameraMode":{"drawMode":0,"name":"Shaded","section":"Shading Mode"},"sceneLighting":false,"audioPlay":false,"sceneViewState":{"m_AlwaysRefresh":false,"showFog":true,"showSkybox":false,"showFlares":true,"showImageEffects":true,"showParticleSystems":true,"showVisualEffectGraphs":true,"m_FxEnabled":true},"in2DMode":false,"pivot":{"x":59.784881591796878,"y":1.7036017179489136,"z":23.275466918945314},"rotation":{"x":-0.0013036975869908929,"y":-0.9886943697929382,"z":0.14974060654640199,"w":-0.008610118180513382},"size":2.7532293796539308,"orthographic":false}